verilog/sram_w8.v
module sram_w8 (CLK, WEN, CEN, D, Q, A);
parameter sram_bit = 64;
input CLK;
input WEN;
input CEN;
input [sram_bit-1:0] D;
output reg [sram_bit-1:0] Q;
input [2:0] A;

reg [sram_bit-1:0] memory0;
reg [sram_bit-1:0] memory1;
reg [sram_bit-1:0] memory2;
reg [sram_bit-1:0] memory3;
reg [sram_bit-1:0] memory4;
reg [sram_bit-1:0] memory5;
reg [sram_bit-1:0] memory6;
reg [sram_bit-1:0] memory7;

always @(posedge CLK) begin
    if (!CEN && WEN) begin
        case (A)
            3'b000: Q <= memory0;
            3'b001: Q <= memory1;
            3'b010: Q <= memory2;
            3'b011: Q <= memory3;
            3'b100: Q <= memory4;
            3'b101: Q <= memory5;
            3'b110: Q <= memory6;
            3'b111: Q <= memory7;
        endcase
    end

    else if (!CEN && !WEN) begin
        case (A)
            3'b000: memory0 <= D;
            3'b001: memory1 <= D;
            3'b010: memory2 <= D;
            3'b011: memory3 <= D;
            3'b100: memory4 <= D;
            3'b101: memory5 <= D;
            3'b110: memory6 <= D;
            3'b111: memory7 <= D;
        endcase
    end
end
endmodule

verilog/sram_w16_doubleBuffered_b64.v
module sram_w16_doubleBuffer_b64(D, Q, A, CEN_EVEN, WEN_EVEN, CEN_ODD, WEN_ODD, CLK);
input [63:0] D;
input [3:0] A;
input CEN_EVEN;
input WEN_EVEN;
input CEN_ODD;
input WEN_ODD;
input CLK;
output [63:0] Q;
reg [2:0] A_EVEN, A_ODD;

always @(*) begin
    if (!A[3]) A_EVEN = A[2:0];
    else if (A[3]) A_ODD = A[2:0];
end

sram_w8 #(.sram_bit(64)) sram_w8_inst_even (
    .CLK(CLK),
    .CEN(CEN_EVEN),
    .WEN(WEN_EVEN),
    .D(D),
    .Q(Q),
    .A(A_EVEN)
);

sram_w8 #(.sram_bit(64)) sram_w8_inst_odd (
    .CLK(CLK),
    .CEN(CEN_ODD),
    .WEN(WEN_ODD),
    .D(D),
    .Q(Q),
    .A(A_ODD)
);
endmodule

verilog/sram_doubleBuffered_tb.v
`timescale 1ns / 1ps

module sram_w16_doubleBuffer_b64_tb;

// Inputs
reg [63:0] D;
reg [3:0] A;
reg CEN_EVEN;
reg WEN_EVEN;
reg CEN_ODD;
reg WEN_ODD;
reg CLK;

// Output
wire [63:0] Q;

// Instantiate the Unit Under Test (UUT)
sram_w16_doubleBuffer_b64 uut (
    .D(D), 
    .Q(Q), 
    .A(A), 
    .CEN_EVEN(CEN_EVEN), 
    .WEN_EVEN(WEN_EVEN), 
    .CEN_ODD(CEN_ODD), 
    .WEN_ODD(WEN_ODD), 
    .CLK(CLK)
);

initial begin
    $dumpfile("sram_tb.vcd");
    $dumpvars(0, sram_w16_doubleBuffer_b64_tb);
    // Initialize Inputs
    #0.5 CLK = 1'b0;
    D = 0;
    A = 0;
    CEN_EVEN = 1;
    WEN_EVEN = 1;
    CEN_ODD = 1;
    WEN_ODD = 1;
    #0.5 CLK = 1'b1;
        
    // Add stimulus here
    // Example: Writing to the even bank and reading back
    #0.5 CLK = 1'b0;
    D = 64'hA5A5_A5A5_A5A5_A5A5; // Example data
    A = 4'b0000; // Address in even bank
    CEN_EVEN = 0; // Chip enable for even bank
    WEN_EVEN = 0; // Write enable for even bank
    #0.5 CLK = 1'b1;

    #0.5 CLK = 1'b1;
    CEN_EVEN = 1; WEN_EVEN = 1; // Disable write operation
    #0.5 CLK = 1'b1;

    // Example: Writing to the odd bank and reading back
    #0.5 CLK = 1'b0;
    D = 64'hA5A5_A5A5_A5A5_A5A5; // Example data
    A = 4'b1000; // Address in even bank
    CEN_ODD = 0; // Chip enable for even bank
    WEN_ODD = 0; // Write enable for even bank
    #0.5 CLK = 1'b1;

    #0.5 CLK = 1'b1;
    CEN_ODD = 1; WEN_ODD = 1; // Disable write operation
    #0.5 CLK = 1'b1;
    // More tests can be added following the same pattern
    #10 $finish;
end


endmodule

sram_tb.vcd
$date
	Fri Mar 15 14:35:33 2024
$end
$version
	Icarus Verilog
$end
$timescale
	1ps
$end
$scope module sram_w16_doubleBuffer_b64_tb $end
$var wire 64 ! Q [63:0] $end
$var reg 4 " A [3:0] $end
$var reg 1 # CEN_EVEN $end
$var reg 1 $ CEN_ODD $end
$var reg 1 % CLK $end
$var reg 64 & D [63:0] $end
$var reg 1 ' WEN_EVEN $end
$var reg 1 ( WEN_ODD $end
$scope module uut $end
$var wire 4 ) A [3:0] $end
$var wire 1 # CEN_EVEN $end
$var wire 1 $ CEN_ODD $end
$var wire 1 % CLK $end
$var wire 64 * D [63:0] $end
$var wire 64 + Q [63:0] $end
$var wire 1 ' WEN_EVEN $end
$var wire 1 ( WEN_ODD $end
$var reg 3 , A_EVEN [2:0] $end
$var reg 3 - A_ODD [2:0] $end
$scope module sram_w8_inst_even $end
$var wire 3 . A [2:0] $end
$var wire 1 # CEN $end
$var wire 1 % CLK $end
$var wire 64 / D [63:0] $end
$var wire 1 ' WEN $end
$var reg 64 0 Q [63:0] $end
$var reg 64 1 memory0 [63:0] $end
$var reg 64 2 memory1 [63:0] $end
$var reg 64 3 memory2 [63:0] $end
$var reg 64 4 memory3 [63:0] $end
$var reg 64 5 memory4 [63:0] $end
$var reg 64 6 memory5 [63:0] $end
$var reg 64 7 memory6 [63:0] $end
$var reg 64 8 memory7 [63:0] $end
$upscope $end
$scope module sram_w8_inst_odd $end
$var wire 3 9 A [2:0] $end
$var wire 1 $ CEN $end
$var wire 1 % CLK $end
$var wire 64 : D [63:0] $end
$var wire 1 ( WEN $end
$var reg 64 ; Q [63:0] $end
$var reg 64 < memory0 [63:0] $end
$var reg 64 = memory1 [63:0] $end
$var reg 64 > memory2 [63:0] $end
$var reg 64 ? memory3 [63:0] $end
$var reg 64 @ memory4 [63:0] $end
$var reg 64 A memory5 [63:0] $end
$var reg 64 B memory6 [63:0] $end
$var reg 64 C memory7 [63:0] $end
$upscope $end
$upscope $end
$upscope $end
$enddefinitions $end
#0
$dumpvars
bx C
bx B
bx A
bx @
bx ?
bx >
bx =
bx <
bx ;
bx :
bx 9
bx 8
bx 7
bx 6
bx 5
bx 4
bx 3
bx 2
bx 1
bx 0
bx /
bx .
bx -
bx ,
bx +
bx *
bx )
x(
x'
bx &
x%
x$
x#
bx "
bx !
$end
#500
b0 ,
b0 .
1(
1$
1'
1#
b0 "
b0 )
b0 &
b0 *
b0 /
b0 :
0%
#1000
1%
#1500
0'
0#
b1010010110100101101001011010010110100101101001011010010110100101 &
b1010010110100101101001011010010110100101101001011010010110100101 *
b1010010110100101101001011010010110100101101001011010010110100101 /
b1010010110100101101001011010010110100101101001011010010110100101 :
0%
#2000
b1010010110100101101001011010010110100101101001011010010110100101 1
1%
#2500
1'
1#
#3500
b0 -
b0 9
0(
0$
b1000 "
b1000 )
0%
#4000
b1010010110100101101001011010010110100101101001011010010110100101 <
1%
#4500
1(
1$
